allencv/__init__.py
allencv/common/__init__.py
allencv/common/util.py
allencv/common/testing/__init__.py
allencv/common/testing/test_case.py
allencv/data/__init__.py
allencv/data/dataset_readers/__init__.py
allencv/data/dataset_readers/image_annotation_reader.py
allencv/data/dataset_readers/image_classification_directory.py
allencv/data/dataset_readers/image_dataset_reader.py
allencv/data/dataset_readers/paired_image_reader.py
allencv/data/fields/__init__.py
allencv/data/fields/image_field.py
allencv/data/transforms/__init__.py
allencv/data/transforms/image_transform.py
allencv/models/__init__.py
allencv/models/basic_classifier.py
allencv/models/semantic_segmentation.py
allencv/models/object_detection/__init__.py
allencv/models/object_detection/faster_rcnn.py
allencv/models/object_detection/region_proposal_network.py
allencv/models/object_detection/utils.py
allencv/modules/__init__.py
allencv/modules/decoder_base.py
allencv/modules/encoder_base.py
allencv/modules/im2im_encoders/__init__.py
allencv/modules/im2im_encoders/feedforward_encoder.py
allencv/modules/im2im_encoders/im2im_encoder.py
allencv/modules/im2im_encoders/resnet_encoder.py
allencv/modules/im2vec_encoders/__init__.py
allencv/modules/im2vec_encoders/flatten_encoder.py
allencv/modules/im2vec_encoders/im2vec_encoder.py
allencv/modules/image_decoders/__init__.py
allencv/modules/image_decoders/basic_decoder.py
allencv/modules/image_decoders/image_decoder.py
allencv/modules/image_encoders/__init__.py
allencv/modules/image_encoders/feature_pyramid_encoder.py
allencv/modules/image_encoders/image_encoder.py
allencv/modules/image_encoders/resnet_encoder.py
allencv/nn/__init__.py
allencv/nn/common.py
allencv/predictors/__init__.py
allencv/predictors/image_predictor.py
allencv/service/__init__.py
allencv/service/server_simple.py
allencv/tests/__init__.py
allencv/tests/data/__init__.py
allencv/tests/data/dataset_readers/__init__.py
allencv/tests/data/dataset_readers/image_annotation_reader_test.py
allencv-0.1.3.dist-info/LICENSE
allencv-0.1.3.dist-info/METADATA
allencv-0.1.3.dist-info/WHEEL
allencv-0.1.3.dist-info/top_level.txt
allencv-0.1.3.dist-info/RECORD
