Metadata-Version: 2.1
Name: allencv
Version: 0.1.3
Summary: UNKNOWN
Home-page: UNKNOWN
Author: sethah
License: MIT
Platform: UNKNOWN
Requires-Python: >=3.6.1
Requires-Dist: torch (>=0.4.1)
Requires-Dist: torchvision (==0.3.0)
Requires-Dist: allennlp
Requires-Dist: numpy
Requires-Dist: overrides
Requires-Dist: ipython
Requires-Dist: albumentations
Requires-Dist: Pillow
